{
  "categories": {
    "1": "CMS",
    "2": "Message boards",
    "3": "Database managers",
    "4": "Documentation",
    "5": "Widgets",
    "6": "Ecommerce",
    "7": "Photo galleries",
    "8": "Wikis",
    "9": "Hosting panels",
    "10": "Analytics",
    "11": "Blogs",
    "12": "JavaScript frameworks",
    "13": "Issue trackers",
    "14": "Video players",
    "15": "Comment systems",
    "16": "Captchas",
    "17": "Font scripts",
    "18": "Web frameworks",
    "19": "Miscellaneous",
    "20": "Editors",
    "21": "LMS",
    "22": "Web servers",
    "23": "Hosting",
    "24": "Analytics",
    "25": "Advertising",
    "26": "Network devices",
    "27": "Media servers",
    "28": "Webcams",
    "29": "Printers",
    "30": "Payment processors",
    "31": "Tag managers",
    "32": "Paywalls",
    "33": "CDN",
    "34": "Marketing automation",
    "35": "Web mail",
    "36": "CDN",
    "37": "JavaScript frameworks",
    "38": "Miscellaneous",
    "39": "Editors",
    "40": "LMS",
    "41": "Web servers",
    "42": "Reverse proxies",
    "43": "Security",
    "44": "JavaScript frameworks",
    "45": "Programming languages",
    "46": "Operating systems",
    "47": "Search engines",
    "48": "Webmail",
    "49": "CDN",
    "50": "Web mail",
    "51": "Webcams",
    "52": "Printers",
    "53": "Payment processors",
    "54": "CDN",
    "55": "Security",
    "56": "Marketing automation",
    "57": "Analytics",
    "58": "Advertising",
    "59": "Web frameworks",
    "60": "Miscellaneous",
    "61": "CMS",
    "62": "Message boards",
    "63": "Database",
    "64": "Documentation",
    "65": "Widgets",
    "66": "Ecommerce",
    "67": "Photo galleries",
    "68": "Wikis",
    "69": "Hosting panels",
    "70": "Analytics",
    "71": "Blogs",
    "72": "JavaScript frameworks",
    "73": "Issue trackers",
    "74": "Video players",
    "75": "Comment systems",
    "76": "Captchas",
    "77": "Font scripts",
    "78": "Web frameworks",
    "79": "Miscellaneous",
    "80": "Editors",
    "81": "LMS",
    "82": "Web servers",
    "83": "Hosting",
    "84": "Analytics",
    "85": "Advertising",
    "86": "AI Services",
    "87": "Programming Languages"
  }
}
